psinspect/__init__.py
psinspect/_version.py
psinspect/app.ipynb
psinspect/app.py
psinspect/tests/test_app.py
psinspect-0.1.1.dist-info/LICENSE
psinspect-0.1.1.dist-info/METADATA
psinspect-0.1.1.dist-info/WHEEL
psinspect-0.1.1.dist-info/entry_points.txt
psinspect-0.1.1.dist-info/top_level.txt
psinspect-0.1.1.dist-info/RECORD
