Metadata-Version: 2.1
Name: psinspect
Version: 0.1.1
Summary: Power spectra inspector for the SO LAT experiment
Author: Simons Observatory Collaboration Power Spectrum Task Force
Maintainer-email: Xavier Garrido <xavier.garrido@ijclab.in2p3.fr>
License: 
Project-URL: Homepage, https://github.com/xgarrido/psinspect
Project-URL: Documentation, https://psinspect.readthedocs.io
Project-URL: Source, https://github.com/xgarrido/psinspect
Project-URL: Tracker, https://github.com/xgarrido/psinspect/issues
Project-URL: Licensing, https://github.com/xgarrido/psinspect/blob/master/LICENCE
Keywords: visualisation,pipeline,cosmology
Classifier: Development Status :: 5 - Production/Stable
Classifier: Operating System :: OS Independent
Classifier: Environment :: Console
Classifier: Intended Audience :: Science/Research
Classifier: Topic :: Scientific/Engineering :: Astronomy
Classifier: License :: OSI Approved :: GNU Lesser General Public License v3 (LGPLv3)
Classifier: Programming Language :: Python :: 3.8
Classifier: Programming Language :: Python :: 3.9
Classifier: Programming Language :: Python :: 3.10
Classifier: Programming Language :: Python :: 3.11
Classifier: Programming Language :: Python :: 3.12
Requires-Python: >=3.8.0
License-File: LICENSE
Requires-Dist: colorlog
Requires-Dist: pspipe-utils
Requires-Dist: jupyterlab
Requires-Dist: ipyfilechooser
Requires-Dist: plotly
Requires-Dist: seaborn
Requires-Dist: voila
